README.md
setup.py
speedstersdk/__init__.py
speedstersdk.egg-info/PKG-INFO
speedstersdk.egg-info/SOURCES.txt
speedstersdk.egg-info/dependency_links.txt
speedstersdk.egg-info/requires.txt
speedstersdk.egg-info/top_level.txt
speedstersdk.egg-info/zip-safe
speedstersdk/dormer/__init__.py
speedstersdk/dormer/api.py
speedstersdk/insight/__init__.py
speedstersdk/insight/insights.py
speedstersdk/insight/resolver.py
speedstersdk/processor/__init__.py
speedstersdk/processor/processor.py