Metadata-Version: 1.0
Name: speedstersdk
Version: 0.1.0
Summary: Speedster SDK.
Home-page: http://www.smartdigits.io
Author: SmartDigits Team
Author-email: jetsetme@tid.es
License: Apache 2.0
Platform: UNKNOWN
